pyCIOT/__init__.py
pyCIOT/__main__.py
pyCIOT/config/data_source.json
pyCIOT/config/note
pyCIOT/data/__init__.py
pyCIOT/data/config.py
pyCIOT/data/module.py
pyCIOT/data/air/__init__.py
pyCIOT/data/air/air.py
pyCIOT/data/cctv/__init__.py
pyCIOT/data/cctv/cctv.py
pyCIOT/data/disaster/__init__.py
pyCIOT/data/disaster/disaster.py
pyCIOT/data/disaster/events.py
pyCIOT/data/quake/__init__.py
pyCIOT/data/quake/quake.py
pyCIOT/data/utils/__init__.py
pyCIOT/data/utils/crawler.py
pyCIOT/data/utils/op.py
pyCIOT/data/utils/url.py
pyCIOT/data/utils/tests/__init__.py
pyCIOT/data/utils/tests/test_expand.py
pyCIOT/data/utils/tests/test_filter.py
pyCIOT/data/utils/tests/test_op.py
pyCIOT/data/utils/tests/test_orderBy.py
pyCIOT/data/utils/tests/test_pagination.py
pyCIOT/data/utils/tests/test_select.py
pyCIOT/data/water/__init__.py
pyCIOT/data/water/water.py
pyCIOT/data/weather/__init__.py
pyCIOT/data/weather/weather.py
pyCIOT-1.1.0.data/data/data_source.json
pyCIOT-1.1.0.data/data/note
pyCIOT-1.1.0.dist-info/LICENSE
pyCIOT-1.1.0.dist-info/METADATA
pyCIOT-1.1.0.dist-info/WHEEL
pyCIOT-1.1.0.dist-info/top_level.txt
pyCIOT-1.1.0.dist-info/RECORD
