Metadata-Version: 2.1
Name: pyCIOT
Version: 1.1.0
Summary: Simple python module for retrieving data from Civil IOT Taiwan Data Service Platform
Home-page: https://github.com/IISNRL/pyCIOT
Author: cclljj
Author-email: cclljj@iis.sinica.edu.tw
Project-URL: Documentation, https://learnciot.github.io/
Project-URL: Source, https://github.com/IISNRL/pyCIOT
Project-URL: Bug Tracker, https://github.com/IISNRL/pyCIOT/issues
Classifier: Programming Language :: Python :: 3
Classifier: License :: OSI Approved :: MIT License
Classifier: Operating System :: OS Independent
Requires-Python: >=3.6
License-File: LICENSE
Requires-Dist: requests (==2.28.0)
Requires-Dist: xmltodict (==0.13.0)
